typecli/__init__.py
typecli/lib.py
typecli-0.2.3.dist-info/licenses/LICENSE
typecli-0.2.3.dist-info/METADATA
typecli-0.2.3.dist-info/WHEEL
typecli-0.2.3.dist-info/top_level.txt
typecli-0.2.3.dist-info/RECORD
