Metadata-Version: 2.4
Name: typecli
Version: 0.2.3
Summary: A declarative CLI Parser
Author-email: peichenzh <1981336562@qq.com>
License-Expression: MIT
Classifier: Programming Language :: Python :: 3
Requires-Python: >=3.9
License-File: LICENSE
Dynamic: license-file
